ltoolboxLib/__init__.py
ltoolboxlib-1.2.1.dist-info/licenses/LICENSE
ltoolboxlib-1.2.1.dist-info/METADATA
ltoolboxlib-1.2.1.dist-info/WHEEL
ltoolboxlib-1.2.1.dist-info/top_level.txt
ltoolboxlib-1.2.1.dist-info/RECORD
