Metadata-Version: 2.4
Name: ltoolboxLib
Version: 1.2.1
Summary: Python utilities for dynamic strings, sandboxed files, multiuse-case classes, and ANSI colors
Author-email: StrawberryMilcRivers <chocomilccy@gmail.com>
License-Expression: MIT
Requires-Python: >=3.8
License-File: LICENSE
Requires-Dist: pyperclip>=1.8.0
Requires-Dist: requests>=2.25.0
Requires-Dist: win10toast>=0.9.0; platform_system == "Windows"
Provides-Extra: dev
Requires-Dist: pytest; extra == "dev"
Requires-Dist: black; extra == "dev"
Requires-Dist: mypy; extra == "dev"
Dynamic: license-file
